klusterpy/__init__.py
klusterpy/cluster/__init__.py
klusterpy/cluster/agglomerative.py
klusterpy/cluster/dbscan.py
klusterpy/cluster/kmeans.py
klusterpy/cluster/kmedoids.py
klusterpy/metric/__init__.py
klusterpy/metric/distance.py
klusterpy-0.0.2.dist-info/METADATA
klusterpy-0.0.2.dist-info/RECORD
klusterpy-0.0.2.dist-info/WHEEL
klusterpy-0.0.2.dist-info/top_level.txt
