Metadata-Version: 2.1
Name: klusterpy
Version: 0.0.2
Summary: Python Machine Learning Clustering Library
Home-page: https://github.com/wijayaerick/klusterpy
Author: Erick Wijaya
Author-email: wijaya.erick52@gmail.com
License: UNKNOWN
Platform: UNKNOWN
Classifier: Intended Audience :: Developers
Classifier: Intended Audience :: Education
Classifier: Intended Audience :: Information Technology
Classifier: Programming Language :: Python :: 3
Classifier: License :: OSI Approved :: MIT License
Classifier: Operating System :: OS Independent
Classifier: Topic :: Education
Classifier: Topic :: Scientific/Engineering :: Artificial Intelligence
Requires-Python: >=3
Requires-Dist: numpy
